embargo/__init__.py
embargo/audit.py
embargo/chaos.py
embargo/cli.py
embargo/config.py
embargo/core.py
embargo/errors.py
embargo/host.py
embargo/net.py
embargo/state.py
embargo/state_machine.py
embargo/utils.py
embargo/version.py
embargo/api/__init__.py
embargo/api/manager.py
embargo/api/rest.py
embargo/tests/__init__.py
embargo/tests/helpers.py
embargo/tests/test_audit.py
embargo/tests/test_chaos.py
embargo/tests/test_cli.py
embargo/tests/test_config.py
embargo/tests/test_core.py
embargo/tests/test_host.py
embargo/tests/test_integration.py
embargo/tests/test_integration_rest.py
embargo/tests/test_net.py
embargo/tests/test_rest.py
embargo/tests/test_state.py
embargo/tests/util.py
embargo-0.1.1.dist-info/LICENSE
embargo-0.1.1.dist-info/METADATA
embargo-0.1.1.dist-info/WHEEL
embargo-0.1.1.dist-info/entry_points.txt
embargo-0.1.1.dist-info/top_level.txt
embargo-0.1.1.dist-info/RECORD
