Metadata-Version: 2.1
Name: embargo
Version: 0.1.1
Summary: Embargo: network fault testing with Docker
Home-page: https://github.com/dgraph-io/embargo
Author: David LaBissoniere
Author-email: david@labisso.com
Maintainer: Martin Martinez Rivera
Maintainer-email: martinmr@dgraph.io
License: UNKNOWN
Platform: UNKNOWN
Classifier: Development Status :: 3 - Alpha
Classifier: Intended Audience :: Developers
Classifier: Natural Language :: English
Classifier: License :: OSI Approved :: Apache Software License
Classifier: Programming Language :: Python
Classifier: Programming Language :: Python :: 3.6
Classifier: Programming Language :: Python :: 3.7
Requires-Dist: PyYAML (<6.0,>=5.1)
Requires-Dist: clint (<0.6,>=0.5.1)
Requires-Dist: docker (>=3.7<4.0)
Requires-Dist: six (>=1.12.0)
Requires-Dist: flask (<1.0,>=0.10.1)
Requires-Dist: gevent (<1.5,>=1.4)
Provides-Extra: test
Requires-Dist: PyYAML (<6.0,>=5.1) ; extra == 'test'
Requires-Dist: clint (<0.6,>=0.5.1) ; extra == 'test'
Requires-Dist: docker (>=3.7<4.0) ; extra == 'test'
Requires-Dist: six (>=1.12.0) ; extra == 'test'
Requires-Dist: flask (<1.0,>=0.10.1) ; extra == 'test'
Requires-Dist: gevent (<1.5,>=1.4) ; extra == 'test'
Requires-Dist: coverage ; extra == 'test'
Requires-Dist: nose ; extra == 'test'
Requires-Dist: mock ; extra == 'test'
Requires-Dist: Flask-Testing (<0.6.0,>=0.5.0) ; extra == 'test'
